void_object/__init__.py
void_object-0.1.3.dist-info/LICENSE
void_object-0.1.3.dist-info/WHEEL
void_object-0.1.3.dist-info/METADATA
void_object-0.1.3.dist-info/RECORD
