Metadata-Version: 2.1
Name: void-object
Version: 0.1.3
Summary: Void Object for Python
Home-page: https://github.com/marcosfede/void-object
Keywords: void,null pattern,null object,proxy
Author: Federico Marcos
Author-email: marcosfede@gmail.com
Requires-Python: >=3.4,<4.0
Classifier: Programming Language :: Python :: 3
Classifier: Programming Language :: Python :: 3.4
Classifier: Programming Language :: Python :: 3.5
Classifier: Programming Language :: Python :: 3.6
Classifier: Programming Language :: Python :: 3.7
Project-URL: Repository, https://github.com/marcosfede/void-object
